kubetorch/__init__.py
kubetorch/cli.py
kubetorch/cli_utils.py
kubetorch/config.py
kubetorch/constants.py
kubetorch/data_store/__init__.py
kubetorch/data_store/data_store_client.py
kubetorch/data_store/data_store_cmds.py
kubetorch/data_store/design.md
kubetorch/data_store/gpu_transfer.py
kubetorch/data_store/key_utils.py
kubetorch/data_store/metadata_client.py
kubetorch/data_store/pod_data_server.py
kubetorch/data_store/rsync_client.py
kubetorch/data_store/types.py
kubetorch/data_store/websocket_tunnel.py
kubetorch/distributed/__init__.py
kubetorch/distributed/utils.py
kubetorch/docs/Makefile
kubetorch/docs/__init__.py
kubetorch/docs/_ext/json_globaltoc.py
kubetorch/docs/api/cli.rst
kubetorch/docs/api/python/app.rst
kubetorch/docs/api/python/cls.rst
kubetorch/docs/api/python/compute.rst
kubetorch/docs/api/python/config.rst
kubetorch/docs/api/python/data_store.rst
kubetorch/docs/api/python/fn.rst
kubetorch/docs/api/python/image.rst
kubetorch/docs/api/python/secret.rst
kubetorch/docs/api/python/volumes.rst
kubetorch/docs/api/python/workload_configs.rst
kubetorch/docs/api/python.rst
kubetorch/docs/conf.py
kubetorch/docs/index.rst
kubetorch/docs/requirements.txt
kubetorch/globals.py
kubetorch/logger.py
kubetorch/provisioning/__init__.py
kubetorch/provisioning/autoscaling.py
kubetorch/provisioning/constants.py
kubetorch/provisioning/design.md
kubetorch/provisioning/service_manager.py
kubetorch/provisioning/templates/deployment_template.yaml
kubetorch/provisioning/templates/knative_service_template.yaml
kubetorch/provisioning/templates/kt_setup_template.sh.j2
kubetorch/provisioning/templates/pod_template.yaml
kubetorch/provisioning/templates/raycluster_template.yaml
kubetorch/provisioning/utils.py
kubetorch/resources/__init__.py
kubetorch/resources/callables/__init__.py
kubetorch/resources/callables/cls/__init__.py
kubetorch/resources/callables/cls/cls.py
kubetorch/resources/callables/fn/__init__.py
kubetorch/resources/callables/fn/fn.py
kubetorch-0.4.1.dist-info/METADATA
kubetorch-0.4.1.dist-info/WHEEL
kubetorch-0.4.1.dist-info/entry_points.txt
kubetorch-0.4.1.dist-info/RECORD
