Metadata-Version: 2.4
Name: kubetorch
Version: 0.4.1
Summary: A Fast, Pythonic, 'Serverless' Interface for Running ML Workloads on Kubernetes
License: Apache 2.0
Author: Runhouse Team
Requires-Python: >=3.9,<4.0
Classifier: License :: OSI Approved :: Apache Software License
Classifier: License :: Other/Proprietary License
Classifier: Programming Language :: Python :: 3
Classifier: Programming Language :: Python :: 3.9
Classifier: Programming Language :: Python :: 3.10
Classifier: Programming Language :: Python :: 3.11
Classifier: Programming Language :: Python :: 3.12
Classifier: Programming Language :: Python :: 3.13
Classifier: Programming Language :: Python :: 3.14
Classifier: Topic :: Software Development :: Libraries :: Python Modules
Classifier: Topic :: System :: Distributed Computing
Provides-Extra: client
Provides-Extra: docs
Provides-Extra: otel
Provides-Extra: server
Requires-Dist: fastapi ; extra == "server"
Requires-Dist: httpx (>=0.28.0,<0.29.0)
Requires-Dist: jinja2 (>=3.0)
Requires-Dist: myst-parser ; extra == "docs"
Requires-Dist: opentelemetry-api ; extra == "otel"
Requires-Dist: opentelemetry-distro ; extra == "otel"
Requires-Dist: opentelemetry-exporter-otlp ; extra == "otel"
Requires-Dist: opentelemetry-exporter-prometheus ; extra == "otel"
Requires-Dist: opentelemetry-instrumentation ; extra == "otel"
Requires-Dist: opentelemetry-instrumentation-fastapi ; extra == "otel"
Requires-Dist: opentelemetry-instrumentation-httpx ; extra == "otel"
Requires-Dist: opentelemetry-instrumentation-logging ; extra == "otel"
Requires-Dist: opentelemetry-sdk ; extra == "otel"
Requires-Dist: prometheus-client ; extra == "server" or extra == "otel"
Requires-Dist: pydantic (>=2.5.0)
Requires-Dist: python-json-logger ; extra == "server"
Requires-Dist: pyyaml (>=6.0,<7.0)
Requires-Dist: rich ; extra == "client"
Requires-Dist: sphinx ; extra == "docs"
Requires-Dist: sphinx-autodoc-typehints ; extra == "docs"
Requires-Dist: sphinx-book-theme ; extra == "docs"
Requires-Dist: typer ; extra == "client"
Requires-Dist: uvicorn[standard] ; extra == "server"
Requires-Dist: websocket-client (>=1.6.0,<2.0.0)
Requires-Dist: websockets (>=15.0,<16.0)
Project-URL: Documentation, https://www.run.house/kubetorch/introduction
Project-URL: Homepage, https://run.house
Project-URL: Repository, https://github.com/run-house/kubetorch
